pydictvalidator/__init__.py
pydictvalidator/validator.py
pydictvalidator-1.0.1.dist-info/METADATA
pydictvalidator-1.0.1.dist-info/WHEEL
pydictvalidator-1.0.1.dist-info/top_level.txt
pydictvalidator-1.0.1.dist-info/RECORD
