Metadata-Version: 2.1
Name: pydictvalidator
Version: 1.0.1
Summary: A Python package to validate JSON dictionaries
Home-page: https://github.com/PandiselviGIT/pydictvalidator
Author: Pandiselvi
Author-email: pandiselvi024@gmail.com
Classifier: Programming Language :: Python :: 3
Classifier: License :: OSI Approved :: MIT License
Classifier: Operating System :: OS Independent
Requires-Python: >=3.6
